xdatatrees/__init__.py
xdatatrees/xdatatrees.py
xdatatrees-0.1.3.dist-info/METADATA
xdatatrees-0.1.3.dist-info/WHEEL
xdatatrees-0.1.3.dist-info/licenses/LICENSE
xdatatrees-0.1.3.dist-info/RECORD
