Metadata-Version: 2.4
Name: xdatatrees
Version: 0.1.3
Summary: An extension/wrapper for the `datatrees`/`dataclasses` library that adds powerful XML serialization and deserialization capabilities to your dataclasses.
Project-URL: Homepage, https://github.com/owebeeone/xdatatrees
Project-URL: Bug Tracker, https://github.com/owebeeone/xdatatrees/issues
Author-email: Gianni Mariani <gianni@mariani.ws>
License-File: LICENSE
Classifier: License :: OSI Approved :: GNU Lesser General Public License v2 or later (LGPLv2+)
Classifier: Operating System :: OS Independent
Classifier: Programming Language :: Python :: 3
Requires-Python: >=3.10
Requires-Dist: datatrees>=0.3.6
Requires-Dist: lxml>=4.6.0
Provides-Extra: test
Requires-Dist: numpy>=1.20.0; extra == 'test'
Requires-Dist: pytest-cov>=4.0.0; extra == 'test'
Requires-Dist: pytest>=7.0.0; extra == 'test'
